[
  {
    "id": 16016882,
    "headline": "Apple Plans for More Workers to Go Back to Offices Over Months",
    "summary": "",
    "symbols": [
      "AAPL"
    ],
    "source": "",
    "url": "https://www.benzinga.com/news/20/05/16016882/apple-plans-for-more-workers-to-go-back-to-offices-over-months",
    "created_at": "2020-05-12T22:07:02Z"
  },
  {
    "id": 16014764,
    "headline": "Short-Line Railroads Prove To Be Appealing Investments",
    "summary": "Private equity funds and other investors are scouring 35,000 miles of North American short-line rail track for deals even as the industry sees one of the biggest volume drops since 2008. ",
    "symbols": [
      "CSX"
    ],
    "source": "",
    "url": "https://www.benzinga.com/markets/20/05/16014764/short-line-railroads-prove-to-be-appealing-investments",
    "created_at": "2020-05-12T20:25:03Z"
  },
  {
    "id": 16015473,
    "headline": "UPDATE: Under The Terms Of The License Agreement Signed With Gilead, Mylan Has Rights To Manufacture And Distribute Remdesivir In 127 Low- And Middle-Income Countries, Including India.",
    "summary": "",
    "symbols": [
      "GILD",
      "MYL"
    ],
    "source": "",
    "url": "https://www.benzinga.com/general/biotech/20/05/16015473/update-under-the-terms-of-the-license-agreement-signed-with-gilead-mylan-has-rights-to-manufactur",
    "created_at": "2020-05-12T20:19:16Z"
  },
  {
    "id": 16015436,
    "headline": "Mylan To Supply Investigational Antiviral Remdesivir For The Potential Treatment Of Coronavirus/COVID-19",
    "summary": "",
    "symbols": [
      "GILD",
      "MYL"
    ],
    "source": "",
    "url": "https://www.benzinga.com/general/biotech/20/05/16015436/mylan-to-supply-investigational-antiviral-remdesivir-for-the-potential-treatment-of-coronavirusco",
    "created_at": "2020-05-12T20:17:42Z"
  },
  {
    "id": 16013591,
    "headline": "PepsiCo Wants To Ship Beverages, Snacks To Your Home",
    "summary": "Beverage and snack giant PepsiCo, Inc. (NASDAQ: PEP) announced Tuesday the launch of two direct-to-consumer portals, PantryShop.com and Snack",
    "symbols": [
      "PEP"
    ],
    "source": "",
    "url": "https://www.benzinga.com/news/20/05/16013591/pepsico-wants-to-ship-beverages-snacks-to-your-home",
    "created_at": "2020-05-12T19:15:02Z"
  },
  {
    "id": 16012403,
    "headline": "Musk Reopens Tesla Plant Despite County Orders",
    "summary": "Tesla Inc&#39;s (NASDAQ: TSLA) California plant reopened after Elon Musk defied orders aimed at containing the spread of COVID-19. Musk asked to be the only person arrested, if it comes to that, he tweeted on Monday.",
    "symbols": [
      "F",
      "FCAU",
      "GM",
      "MS",
      "TSLA"
    ],
    "source": "",
    "url": "https://www.benzinga.com/markets/20/05/16012403/musk-reopens-tesla-plant-despite-county-orders",
    "created_at": "2020-05-12T18:41:49Z"
  },
  {
    "id": 16014251,
    "headline": "Gilead Confirms Non-Exclusive Voluntary License Deal For Distribution Of Remdesivir With 5 Generic Makers In 127 Countries",
    "summary": "",
    "symbols": [
      "GILD"
    ],
    "source": "",
    "url": "https://www.benzinga.com/news/20/05/16014251/gilead-confirms-non-exclusive-voluntary-license-deal-for-distribution-of-remdesivir-with-5-generic-m",
    "created_at": "2020-05-12T18:40:02Z"
  },
  {
    "id": 16001948,
    "headline": "A Potentially Profitable Options Trade In Shopify",
    "summary": "Shopify Inc (NASDAQ: SHOP) has arguably been the stock to own in 2020. Buoyed by a global flight to e-commerce as a result of COVID-19, shares of the e-commerce platform for small businesses are up 43% in 2020. ",
    "symbols": [
      "SHOP"
    ],
    "source": "",
    "url": "https://www.benzinga.com/trading-ideas/long-ideas/20/05/16001948/a-potentially-profitable-options-trade-in-shopify",
    "created_at": "2020-05-12T18:33:23Z"
  },
  {
    "id": 16002603,
    "headline": "Here's A Bullish Options Play On Gilead",
    "summary": "With the markets in turmoil over the coronavirus, no stock has embodied the unpredictability of today more than Gilead Sciences (NASDAQ: GILD). ",
    "symbols": [
      "GILD"
    ],
    "source": "",
    "url": "https://www.benzinga.com/trading-ideas/long-ideas/20/05/16002603/heres-a-bullish-options-play-on-gilead",
    "created_at": "2020-05-12T18:28:54Z"
  },
  {
    "id": 16014151,
    "headline": "Microvision Shares Fall To Session Low, Still Up 11% For Session; Traders Circulate Tweet 'PR team for Microsoft said there is no legitimacy regarding acquiring of $MVIS...'",
    "summary": "",
    "symbols": [
      "MSFT",
      "MVIS"
    ],
    "source": "",
    "url": "https://www.benzinga.com/m-a/20/05/16014151/microvision-shares-fall-to-session-low-still-up-11-for-session-traders-circulate-tweet-pr-team-for-m",
    "created_at": "2020-05-12T18:24:10Z"
  },
  {
    "id": 16014145,
    "headline": "'Gilead strikes licensing agreements w 5 cos (Cipla Ltd., Ferozsons Laboratories, Hetero Labs Ltd., Jubilant Lifesciences and Mylan) to manufacture remdesivir in 127 countries, royalty-free until WHO declares end of global public health emergency' -Tweet",
    "summary": "",
    "symbols": [
      "GILD",
      "SPY"
    ],
    "source": "",
    "url": "https://www.benzinga.com/news/20/05/16014145/gilead-strikes-licensing-agreements-w-5-cos-cipla-ltd-ferozsons-laboratories-hetero-labs-ltd-jubilan",
    "created_at": "2020-05-12T18:22:11Z"
  },
  {
    "id": 16012853,
    "headline": "Here's What Kara Swisher And Chamath Palihapitiya Think About Elon Musk's Threats To Leave California",
    "summary": "Elon Musk may be irking his factory hosts with threats of legal action and corporate emigration, but he isn’t losing investors yet.",
    "symbols": [
      "AMZN",
      "TSLA"
    ],
    "source": "",
    "url": "https://www.benzinga.com/news/20/05/16012853/heres-what-kara-swisher-and-chamath-palihapitiya-think-about-elon-musks-threats-to-leave-california",
    "created_at": "2020-05-12T18:15:05Z"
  },
  {
    "id": 16001901,
    "headline": "2 Options Strategies for NVIDIA Ahead Of Earnings",
    "summary": "After selling off with the rest of the market in March, shares of Nvidia Corporation (NASDAQ: NVDA) are back near all-time highs.",
    "symbols": [
      "NVDA"
    ],
    "source": "",
    "url": "https://www.benzinga.com/news/earnings/20/05/16001901/2-options-strategies-for-nvidia-ahead-of-earnings",
    "created_at": "2020-05-12T18:10:27Z"
  },
  {
    "id": 16012405,
    "headline": "Marriott International First Quarter Earnings Report; 'Another One Bites the Dust'",
    "summary": "On Monday, shares of Marriott International Inc (NASDAQ: MAR) fell as first-quarter earnings missed expectations.",
    "symbols": [
      "H",
      "MAR"
    ],
    "source": "",
    "url": "https://www.benzinga.com/news/earnings/20/05/16012405/marriott-international-first-quarter-earnings-report-another-one-bites-the-dust",
    "created_at": "2020-05-12T18:07:50Z"
  },
  {
    "id": 16012406,
    "headline": "Caution Ahead: Biggest Blue-Chips Seek Change, Innovation Post-COVID-19",
    "summary": "The origin of the term blue-chip comes from the world of poker, where blue-colored chips are the highest available denomination in the game. In finance, however, blue-chips are among the highest valued companies.",
    "symbols": [
      "AAPL",
      "AMZN",
      "BA",
      "BAC",
      "CVX",
      "FB",
      "MSFT",
      "PYPL",
      "V",
      "XOM"
    ],
    "source": "",
    "url": "https://www.benzinga.com/markets/20/05/16012406/caution-ahead-biggest-blue-chips-seek-change-innovation-post-covid-19",
    "created_at": "2020-05-12T17:49:22Z"
  },
  {
    "id": 16013259,
    "headline": "AMC's Stock Still In The Spotlight As Wall Street Digests Amazon Rumor",
    "summary": "Movie theater chain AMC Entertainment Holdings Inc (NYSE: AMC) is reportedly in the crosshairs of Amazon.com, Inc. (NASDAQ: ",
    "symbols": [
      "AMC",
      "AMZN"
    ],
    "source": "",
    "url": "https://www.benzinga.com/analyst-ratings/analyst-color/20/05/16013259/amcs-stock-still-in-the-spotlight-as-wall-street-digests-amazon-rumor",
    "created_at": "2020-05-12T17:42:50Z"
  },
  {
    "id": 16013531,
    "headline": "Google, On April 28, Said 'We're Adding Roughly 3 Million New Users Every Day For Google Meet'",
    "summary": "",
    "symbols": [
      "GOOG",
      "GOOGL"
    ],
    "source": "",
    "url": "https://www.benzinga.com/news/20/05/16013531/google-on-april-28-said-were-adding-roughly-3-million-new-users-every-day-for-google-meet",
    "created_at": "2020-05-12T17:10:47Z"
  },
  {
    "id": 16013478,
    "headline": "Zoom Shares Ticking Lower; Google Says Have Re-Engineered Google Meet, Originally Built For Secure Business Meetings, To Make It Free And Available To All",
    "summary": "",
    "symbols": [
      "GOOG",
      "GOOGL",
      "ZM"
    ],
    "source": "",
    "url": "https://www.benzinga.com/news/20/05/16013478/zoom-shares-ticking-lower-google-says-have-re-engineered-google-meet-originally-built-for-secure-bus",
    "created_at": "2020-05-12T17:05:31Z"
  },
  {
    "id": 16013142,
    "headline": "PreMarket Prep Stock Of The Day: Simon Property Group",
    "summary": "Benzinga&#39;s PreMarket Prep airs every morning from 8-9 a.m. ET. During that fast-paced, highly informative hour, traders and investors tune in to get the major news of the day, the catalysts behind those moves and the corresponding price action for the upcoming session.",
    "symbols": [
      "AMZN",
      "JCP",
      "M",
      "SPG",
      "TCO"
    ],
    "source": "",
    "url": "https://www.benzinga.com/news/earnings/20/05/16013142/premarket-prep-stock-of-the-day-simon-property-group",
    "created_at": "2020-05-12T16:58:11Z"
  },
  {
    "id": 16013069,
    "headline": "Amazon Shares Unaffected Amid Report Coalition Of 13 US Attorney Generals Have Asked Co. To Provide Data About Infections, Deaths Among Its Workers, Evidence Co Is In Compliance With State Paid Sick Leave Laws",
    "summary": "",
    "symbols": [
      "AMZN"
    ],
    "source": "",
    "url": "https://www.benzinga.com/news/20/05/16013069/amazon-shares-unaffected-amid-report-coalition-of-13-us-attorney-generals-have-asked-co-to-provide-d",
    "created_at": "2020-05-12T16:29:24Z"
  },
  {
    "id": 16013064,
    "headline": "Monster Beverage Shares Volatile On Spike In Volume As Hearing Stock Mentioned On CNBC",
    "summary": "",
    "symbols": [
      "MNST"
    ],
    "source": "",
    "url": "https://www.benzinga.com/trading-ideas/movers/20/05/16013064/monster-beverage-shares-volatile-on-spike-in-volume-as-hearing-stock-mentioned-on-cnbc",
    "created_at": "2020-05-12T16:28:35Z"
  },
  {
    "id": 16013044,
    "headline": "60 Stocks Moving In Tuesday's Mid-Day Session",
    "summary": "Gainers\n\n\n",
    "symbols": [
      "ACER",
      "ADES",
      "AKRX",
      "ALDX",
      "APOP",
      "ARA",
      "ARLO",
      "AXLA",
      "BGS",
      "CBAY",
      "CDLX",
      "CELH",
      "CHAP",
      "CHEF",
      "CHK",
      "CLPR",
      "CRC",
      "CSPR",
      "CTRA",
      "CVLT",
      "DDOG",
      "DRIO",
      "DRRX",
      "EB",
      "ECPG",
      "ERI",
      "FLNT",
      "FOSL",
      "GDOT",
      "GMDA",
      "GNFT",
      "GNUS",
      "GRUB",
      "GSKY",
      "HOME",
      "HSDT",
      "IIVI",
      "KOP",
      "MVIS",
      "NBRV",
      "NEPT",
      "NNVC",
      "NVAX",
      "PLSE",
      "QUIK",
      "RAND",
      "SGLB",
      "SGRY",
      "SIEN",
      "SLGG",
      "SQNS",
      "SRNE",
      "UAVS",
      "UNFI",
      "UNIT",
      "UPWK",
      "VEDL",
      "VERI",
      "WTRH",
      "YRCW"
    ],
    "source": "",
    "url": "https://www.benzinga.com/news/20/05/16013044/60-stocks-moving-in-tuesdays-mid-day-session",
    "created_at": "2020-05-12T16:26:53Z"
  },
  {
    "id": 16013008,
    "headline": "Blink Charging Shares Spike To Session High On Volume As Traders Circulate Alert From Buy Sell Short Suggesting Blink Could Be A Play On Rallies In Tesla, VectoIQ",
    "summary": "",
    "symbols": [
      "BLNK",
      "TSLA"
    ],
    "source": "",
    "url": "https://www.benzinga.com/news/20/05/16013008/blink-charging-shares-spike-to-session-high-on-volume-as-traders-circulate-alert-from-buy-sell-short",
    "created_at": "2020-05-12T16:22:17Z"
  },
  {
    "id": 16012960,
    "headline": "Jubilant Life Sciences Signs Non-Exclusive License Deal For Selling Gilead's Remdesivir In 127 Countries Including India; BZ NOTE: Jubilant Not Publicly Traded In US",
    "summary": "",
    "symbols": [
      "GILD"
    ],
    "source": "",
    "url": "https://www.benzinga.com/news/20/05/16012960/jubilant-life-sciences-signs-non-exclusive-license-deal-for-selling-gileads-remdesivir-in-127-countr",
    "created_at": "2020-05-12T16:18:17Z"
  },
  {
    "id": 16010847,
    "headline": "Tilray Investors Overreacted To A Good Q1 Print, Says Cantor Fitzgerald",
    "summary": "Tilray Inc (NASDAQ: TLRY) reported stable first-quarter results Monday, beating expectations across key metrics.",
    "symbols": [
      "COST",
      "TLRY"
    ],
    "source": "",
    "url": "https://www.benzinga.com/analyst-ratings/analyst-color/20/05/16010847/tilray-investors-overreacted-to-a-good-q1-print-says-cantor-fitzgerald",
    "created_at": "2020-05-12T16:17:31Z"
  },
  {
    "id": 16012893,
    "headline": "Citigroup Maintains Buy on Alphabet, Raises Price Target to $1600",
    "summary": "",
    "symbols": [
      "GOOGL"
    ],
    "source": "",
    "url": "https://www.benzinga.com/news/20/05/16012893/citigroup-maintains-buy-on-alphabet-raises-price-target-to-1600",
    "created_at": "2020-05-12T16:12:52Z"
  },
  {
    "id": 16012868,
    "headline": "Citigroup Maintains Buy on Linde, Raises Price Target to $216",
    "summary": "",
    "symbols": [
      "LIN"
    ],
    "source": "",
    "url": "https://www.benzinga.com/news/20/05/16012868/citigroup-maintains-buy-on-linde-raises-price-target-to-216",
    "created_at": "2020-05-12T16:10:37Z"
  },
  {
    "id": 16011333,
    "headline": "The Fed Makes History Buying $750B In Corporate Bonds",
    "summary": "The Federal Reserve is buying corporate bonds for the first time in an attempt to curb the economic fallout of the coronavirus.",
    "symbols": [
      "BLK",
      "DDS",
      "MDLZ",
      "MO",
      "PYPL",
      "VFC"
    ],
    "source": "",
    "url": "https://www.benzinga.com/news/20/05/16011333/the-fed-makes-history-buying-750b-in-corporate-bonds",
    "created_at": "2020-05-12T16:07:54Z"
  },
  {
    "id": 16012694,
    "headline": "Citigroup Maintains Buy on T-Mobile US, Raises Price Target to $115",
    "summary": "",
    "symbols": [
      "TMUS"
    ],
    "source": "",
    "url": "https://www.benzinga.com/news/20/05/16012694/citigroup-maintains-buy-on-t-mobile-us-raises-price-target-to-115",
    "created_at": "2020-05-12T16:04:45Z"
  },
  {
    "id": 16012542,
    "headline": "'From PepsiCo to GM, Big Advertisers Set to Cancel Commitments to TV Networks' -Breaking WSJ Report",
    "summary": "",
    "symbols": [
      "GM",
      "PEP"
    ],
    "source": "",
    "url": "https://www.benzinga.com/news/20/05/16012542/from-pepsico-to-gm-big-advertisers-set-to-cancel-commitments-to-tv-networks-breaking-wsj-report",
    "created_at": "2020-05-12T15:55:45Z"
  },
  {
    "id": 16012487,
    "headline": "FDA Commissioner: We've Learned A Lot Of Lessons From The 'Remdesivir Situation'",
    "summary": "",
    "symbols": [
      "GILD"
    ],
    "source": "",
    "url": "https://www.benzinga.com/news/20/05/16012487/fda-commissioner-weve-learned-a-lot-of-lessons-from-the-remdesivir-situation",
    "created_at": "2020-05-12T15:49:41Z"
  },
  {
    "id": 16011281,
    "headline": "Amazon Air Picks San Bernardino Airport For Western Hub",
    "summary": "As expected, Amazon Inc&#39;s (NASDAQ: AMZN) newest air hub will be in San Bernardino, California, where feeder aircraft from various cities and trucks from nearby warehouses will arrive with packages to be sorted and redistributed nationwide on outbound airplanes.",
    "symbols": [
      "AMZN",
      "FDX",
      "UPS"
    ],
    "source": "",
    "url": "https://www.benzinga.com/news/20/05/16011281/amazon-air-picks-san-bernardino-airport-for-western-hub",
    "created_at": "2020-05-12T15:28:44Z"
  },
  {
    "id": 16012009,
    "headline": "Mizuho Maintains Buy on Datadog, Raises Price Target to $66",
    "summary": "",
    "symbols": [
      "DDOG"
    ],
    "source": "",
    "url": "https://www.benzinga.com/news/20/05/16012009/mizuho-maintains-buy-on-datadog-raises-price-target-to-66",
    "created_at": "2020-05-12T15:13:05Z"
  },
  {
    "id": 16010047,
    "headline": "Wedbush Polishes Apple Price Target On 'Teflon-Like' Services, iPhone 12 Outlook",
    "summary": "As one of the first U.S. businesses disrupted by the coronavirus, Apple Inc. (NASDAQ: AAPL) seemed to be a model of superior survival techniques.",
    "symbols": [
      "AAPL"
    ],
    "source": "",
    "url": "https://www.benzinga.com/analyst-ratings/analyst-color/20/05/16010047/wedbush-polishes-apple-price-target-on-teflon-like-services-iphone-12-outlook",
    "created_at": "2020-05-12T14:58:17Z"
  },
  {
    "id": 16011551,
    "headline": "BMO Capital Maintains Outperform on Linde, Raises Price Target to $220",
    "summary": "",
    "symbols": [
      "LIN"
    ],
    "source": "",
    "url": "https://www.benzinga.com/news/20/05/16011551/bmo-capital-maintains-outperform-on-linde-raises-price-target-to-220",
    "created_at": "2020-05-12T14:49:50Z"
  },
  {
    "id": 16011524,
    "headline": "BMO Capital Maintains Underperform on Marriott Intl, Raises Price Target to $74",
    "summary": "",
    "symbols": [
      "MAR"
    ],
    "source": "",
    "url": "https://www.benzinga.com/news/20/05/16011524/bmo-capital-maintains-underperform-on-marriott-intl-raises-price-target-to-74",
    "created_at": "2020-05-12T14:48:16Z"
  },
  {
    "id": 16011481,
    "headline": "Philly Fed Pres Harker Says Evidence Is Overwhelming Something Needs To Be Done To Help Train Workers For New Careers",
    "summary": "",
    "symbols": [
      "CNI",
      "CP",
      "CSX",
      "KSU",
      "NSC",
      "UNP"
    ],
    "source": "",
    "url": "https://www.benzinga.com/news/20/05/16011481/philly-fed-pres-harker-says-evidence-is-overwhelming-something-needs-to-be-done-to-help-train-worker",
    "created_at": "2020-05-12T14:45:18Z"
  },
  {
    "id": 16011450,
    "headline": "JP Morgan Maintains Overweight on Datadog, Raises Price Target to $65",
    "summary": "",
    "symbols": [
      "DDOG"
    ],
    "source": "",
    "url": "https://www.benzinga.com/news/20/05/16011450/jp-morgan-maintains-overweight-on-datadog-raises-price-target-to-65",
    "created_at": "2020-05-12T14:42:36Z"
  },
  {
    "id": 16011435,
    "headline": "Stocks That Hit 52-Week Highs On Tuesday",
    "summary": "Tuesday morning saw 85 companies set new 52-week highs.",
    "symbols": [
      "ACMR",
      "ALLO",
      "ARCT",
      "ASND",
      "ATRC",
      "BIO",
      "BSGM",
      "CABO",
      "CCXI",
      "CELH",
      "CJJD",
      "CMCL",
      "CMG",
      "COUP",
      "CRDF",
      "CTMX",
      "CTSO",
      "CYTK",
      "DDOG",
      "DOCU",
      "DSS",
      "EBAY",
      "EBS",
      "EGF",
      "ELA",
      "ENPH",
      "EVBG",
      "EXEL",
      "FLWS",
      "FSLY",
      "FVRR",
      "GFL",
      "GIS",
      "GMAB",
      "GNSS",
      "HAIN",
      "HALO",
      "IIVI",
      "IMVT",
      "KNSA",
      "LOGI",
      "LSCC",
      "LVGO",
      "MARK",
      "MASI",
      "MDB",
      "MGNX",
      "MPWR",
      "MRNA",
      "MSCI",
      "MYOK",
      "NBR",
      "NERV",
      "NTRA",
      "NVAX",
      "NVDA",
      "NVMI",
      "PDD",
      "PFSW",
      "PRPL",
      "PTON",
      "RNG",
      "SFM",
      "SHOP",
      "SPT",
      "SPTN",
      "TBIO",
      "TBLT",
      "TECH",
      "TGTX",
      "THW",
      "TREX",
      "TW",
      "UNFI",
      "UTHR",
      "VOXX",
      "VRTX",
      "VTIQ",
      "W",
      "WIX",
      "WST",
      "XLRN",
      "ZLAB",
      "ZTO",
      "ZYXI"
    ],
    "source": "",
    "url": "https://www.benzinga.com/news/20/05/16011435/stocks-that-hit-52-week-highs-on-tuesday",
    "created_at": "2020-05-12T14:41:08Z"
  },
  {
    "id": 16011372,
    "headline": "Fauci: Remdesivir Study Was Statistically Significant But Modest Success",
    "summary": "",
    "symbols": [
      "GILD",
      "SPY"
    ],
    "source": "",
    "url": "https://www.benzinga.com/news/20/05/16011372/fauci-remdesivir-study-was-statistically-significant-but-modest-success",
    "created_at": "2020-05-12T14:31:46Z"
  },
  {
    "id": 16011256,
    "headline": "Jefferies Maintains Hold on Datadog, Raises Price Target to $59",
    "summary": "",
    "symbols": [
      "DDOG"
    ],
    "source": "",
    "url": "https://www.benzinga.com/news/20/05/16011256/jefferies-maintains-hold-on-datadog-raises-price-target-to-59",
    "created_at": "2020-05-12T14:17:36Z"
  },
  {
    "id": 16010883,
    "headline": "Benzinga's Top Upgrades, Downgrades For May 12, 2020",
    "summary": "Upgrades\n\n\n",
    "symbols": [
      "ALB",
      "ALDX",
      "AMRX",
      "ARVN",
      "AXTA",
      "CBAY",
      "CLR",
      "CMI",
      "CNP",
      "CRNC",
      "CVX",
      "ES",
      "EVLO",
      "JJSF",
      "KMX",
      "LBTYA",
      "MMC",
      "MRKR",
      "ON",
      "PCAR",
      "PINC",
      "PLSE",
      "PNW",
      "POR",
      "QDEL",
      "SWK",
      "TCP",
      "UNIT",
      "WMB"
    ],
    "source": "",
    "url": "https://www.benzinga.com/markets/penny-stocks/20/05/16010883/benzingas-top-upgrades-downgrades-for-may-12-2020",
    "created_at": "2020-05-12T13:51:03Z"
  },
  {
    "id": 16010843,
    "headline": "Trump Tweets: 'California should let Tesla & @elonmusk open the plant, NOW. It can be done Fast & Safely!'",
    "summary": "",
    "symbols": [
      "TSLA"
    ],
    "source": "",
    "url": "https://www.benzinga.com/news/20/05/16010843/trump-tweets-california-should-let-tesla-elonmusk-open-the-plant-now-it-can-be-done-fast-safely",
    "created_at": "2020-05-12T13:46:11Z"
  },
  {
    "id": 16010602,
    "headline": "Stifel Maintains Buy on Datadog, Raises Price Target to $60",
    "summary": "",
    "symbols": [
      "DDOG"
    ],
    "source": "",
    "url": "https://www.benzinga.com/news/20/05/16010602/stifel-maintains-buy-on-datadog-raises-price-target-to-60",
    "created_at": "2020-05-12T13:26:04Z"
  },
  {
    "id": 16010429,
    "headline": "Intel Reports Its Capital Arm Invests $132M In 11 Technology Startups",
    "summary": "",
    "symbols": [
      "INTC"
    ],
    "source": "",
    "url": "https://www.benzinga.com/m-a/20/05/16010429/intel-reports-its-capital-arm-invests-132m-in-11-technology-startups",
    "created_at": "2020-05-12T13:03:52Z"
  },
  {
    "id": 16010428,
    "headline": "Deutsche Bank Maintains Hold on Marriott Intl, Lowers Price Target to $88",
    "summary": "",
    "symbols": [
      "MAR"
    ],
    "source": "",
    "url": "https://www.benzinga.com/news/20/05/16010428/deutsche-bank-maintains-hold-on-marriott-intl-lowers-price-target-to-88",
    "created_at": "2020-05-12T13:03:36Z"
  },
  {
    "id": 16010075,
    "headline": "'[Elon] will bring back American manufacturing. He's the best we have...' -Jim Cramer",
    "summary": "",
    "symbols": [
      "TSLA"
    ],
    "source": "",
    "url": "https://www.benzinga.com/news/20/05/16010075/elon-will-bring-back-american-manufacturing-hes-the-best-we-have-jim-cramer",
    "created_at": "2020-05-12T12:53:34Z"
  },
  {
    "id": 16010010,
    "headline": "Wedbush Maintains Outperform on Apple, Raises Price Target to $350",
    "summary": "",
    "symbols": [
      "AAPL"
    ],
    "source": "",
    "url": "https://www.benzinga.com/news/20/05/16010010/wedbush-maintains-outperform-on-apple-raises-price-target-to-350",
    "created_at": "2020-05-12T12:43:47Z"
  },
  {
    "id": 16009987,
    "headline": "'Distribution of Key Drug Was Flawed, Says White House Official' -Yesterday WSJ Report",
    "summary": "",
    "symbols": [
      "GILD"
    ],
    "source": "",
    "url": "https://www.benzinga.com/news/20/05/16009987/distribution-of-key-drug-was-flawed-says-white-house-official-yesterday-wsj-report",
    "created_at": "2020-05-12T12:39:16Z"
  },
  {
    "id": 16008037,
    "headline": "Cramer Gives His Opinion On Cisco, Uber And More",
    "summary": "On CNBC&#39;s &#34;Mad Money Lightning Round,&#34; Jim Cramer advised a viewer with a long position in Cisco Systems, Inc. (NASDAQ: CSCO) to wait for the earnings report.",
    "symbols": [
      "CERS",
      "CSCO",
      "HMSY",
      "MRTX",
      "UBER",
      "VRTX",
      "WRK"
    ],
    "source": "",
    "url": "https://www.benzinga.com/media/20/05/16008037/cramer-gives-his-opinion-on-cisco-uber-and-more",
    "created_at": "2020-05-12T12:33:05Z"
  },
  {
    "id": 16009887,
    "headline": "Apple Unveils Update To Logic Pro",
    "summary": "",
    "symbols": [
      "AAPL"
    ],
    "source": "",
    "url": "https://www.benzinga.com/tech/20/05/16009887/apple-unveils-update-to-logic-pro",
    "created_at": "2020-05-12T12:32:14Z"
  },
  {
    "id": 16007624,
    "headline": "Elon Musk Appoints Paint Operations Director To Oversee Fremont Production",
    "summary": "Elon Musk has appointed Richard Miller, a director of paint operations, as head of production at Tesla Inc.’s (NASDAQ: TSLA) Fremont, California factory.",
    "symbols": [
      "TSLA"
    ],
    "source": "",
    "url": "https://www.benzinga.com/news/20/05/16007624/elon-musk-appoints-paint-operations-director-to-oversee-fremont-production",
    "created_at": "2020-05-12T12:24:08Z"
  },
  {
    "id": 16009578,
    "headline": "Morgan Stanley Maintains Equal-Weight on Datadog, Raises Price Target to $60",
    "summary": "",
    "symbols": [
      "DDOG"
    ],
    "source": "",
    "url": "https://www.benzinga.com/news/20/05/16009578/morgan-stanley-maintains-equal-weight-on-datadog-raises-price-target-to-60",
    "created_at": "2020-05-12T12:08:02Z"
  },
  {
    "id": 16008416,
    "headline": "The Daily Biotech Pulse: NASH Disappointment For Genfit, Novavax Lands $384M CEPI Funding For Coronavirus Vaccine, GW Pharma Earnings",
    "summary": "Here&#39;s a roundup of top developments in the biotech space over the last 24 hours:\n\nScaling The Peaks\n\n(Biotech Stocks Hitting 52-week Highs May 11)",
    "symbols": [
      "ACER",
      "ADMP",
      "ADPT",
      "AKBA",
      "ALLO",
      "APOP",
      "ARCT",
      "ATRC",
      "BHC",
      "BIO",
      "BNTX",
      "BSGM",
      "BTAI",
      "CATB",
      "CBAY",
      "CCXI",
      "CLPT",
      "CRIS",
      "CRSP",
      "CTMX",
      "CUE",
      "CYCC",
      "CYTK",
      "DGX",
      "DRIO",
      "DXCM",
      "EBS",
      "GMAB",
      "GNCA",
      "GNFT",
      "GOSS",
      "GWPH",
      "HALO",
      "HZNP",
      "IBB",
      "IMMU",
      "IMVT",
      "KMPH",
      "KNSA",
      "LIFE",
      "MASI",
      "MCRB",
      "MGNX",
      "MNTA",
      "MRKR",
      "MRNA",
      "MYOK",
      "NBIX",
      "NBSE",
      "NERV",
      "NSPR",
      "NTRA",
      "NVAX",
      "NVS",
      "OCX",
      "OPNT",
      "ORIC",
      "OSMT",
      "OSUR",
      "PLSE",
      "PODD",
      "PT",
      "PTGX",
      "QDEL",
      "QGEN",
      "REPH",
      "RGEN",
      "SNY",
      "SSKN",
      "STRO",
      "SWAV",
      "TECH",
      "TGTX",
      "TNDM",
      "TPTX",
      "VIVO",
      "VRTX",
      "WST",
      "XBI",
      "XLRN",
      "ZLAB",
      "ZNTL",
      "ZYXI"
    ],
    "source": "",
    "url": "https://www.benzinga.com/general/biotech/20/05/16008416/the-daily-biotech-pulse-nash-disappointment-for-genfit-novavax-lands-384m-cepi-funding-for-corona",
    "created_at": "2020-05-12T12:06:36Z"
  },
  {
    "id": 16009559,
    "headline": "Credit Suisse Maintains Neutral on Datadog, Raises Price Target to $55",
    "summary": "",
    "symbols": [
      "DDOG"
    ],
    "source": "",
    "url": "https://www.benzinga.com/news/20/05/16009559/credit-suisse-maintains-neutral-on-datadog-raises-price-target-to-55",
    "created_at": "2020-05-12T12:05:48Z"
  },
  {
    "id": 16009423,
    "headline": "10 Biggest Price Target Changes For Tuesday",
    "summary": "\n\tH.C. Wainwright boosted the price target for  Pulse Biosciences Inc  (NASDAQ: PLSE) from $6 to $16. Pulse Biosciences closed at $11.74 on Monday.\n",
    "symbols": [
      "ALB",
      "CBAY",
      "CCXI",
      "CMI",
      "DDOG",
      "EVLO",
      "IIVI",
      "PCAR",
      "PLSE",
      "UAA"
    ],
    "source": "",
    "url": "https://www.benzinga.com/markets/penny-stocks/20/05/16009423/10-biggest-price-target-changes-for-tuesday",
    "created_at": "2020-05-12T12:03:41Z"
  },
  {
    "id": 16008725,
    "headline": "Rosenblatt Maintains Buy on Datadog, Raises Price Target to $75",
    "summary": "",
    "symbols": [
      "DDOG"
    ],
    "source": "",
    "url": "https://www.benzinga.com/news/20/05/16008725/rosenblatt-maintains-buy-on-datadog-raises-price-target-to-75",
    "created_at": "2020-05-12T11:06:31Z"
  },
  {
    "id": 16008440,
    "headline": "Needham Maintains Buy on Datadog, Raises Price Target to $70",
    "summary": "",
    "symbols": [
      "DDOG"
    ],
    "source": "",
    "url": "https://www.benzinga.com/news/20/05/16008440/needham-maintains-buy-on-datadog-raises-price-target-to-70",
    "created_at": "2020-05-12T10:28:09Z"
  },
  {
    "id": 16008392,
    "headline": "A Peek Into The Markets: US Stock Futures Mostly Flat Ahead Of Consumer Price Index",
    "summary": "Pre-open movers",
    "symbols": [
      "DIS",
      "GO",
      "IR",
      "PYPL",
      "TME",
      "WMB"
    ],
    "source": "",
    "url": "https://www.benzinga.com/news/earnings/20/05/16008392/a-peek-into-the-markets-us-stock-futures-mostly-flat-ahead-of-consumer-price-index",
    "created_at": "2020-05-12T10:17:14Z"
  },
  {
    "id": 16008292,
    "headline": "Piper Sandler Downgrades PACCAR to Neutral, Raises Price Target of $73",
    "summary": "",
    "symbols": [
      "PCAR"
    ],
    "source": "",
    "url": "https://www.benzinga.com/news/20/05/16008292/piper-sandler-downgrades-paccar-to-neutral-raises-price-target-of-73",
    "created_at": "2020-05-12T10:08:40Z"
  },
  {
    "id": 16007555,
    "headline": "Amazon Releases AI-Based Enterprise Search Solution Kendra",
    "summary": "On Monday, Amazon Inc. (NASDAQ: AMZN)-owned Amazon Web Services (AWS) launched Kendra, an enterprise search solution powered by machine learning.",
    "symbols": [
      "AMZN",
      "GOOG",
      "GOOGL"
    ],
    "source": "",
    "url": "https://www.benzinga.com/news/20/05/16007555/amazon-releases-ai-based-enterprise-search-solution-kendra",
    "created_at": "2020-05-12T09:41:39Z"
  },
  {
    "id": 16007314,
    "headline": "Musk and Tesla Putting 'Major Pressure' On Alameda County, Say Wedbush Analysts",
    "summary": "The standoff between Alameda County and Tesla Inc.’s (NASDAQ: TSLA) CEO Elon Musk has become a nationa",
    "symbols": [
      "TSLA"
    ],
    "source": "",
    "url": "https://www.benzinga.com/government/20/05/16007314/musk-and-tesla-putting-major-pressure-on-alameda-county-say-wedbush-analysts",
    "created_at": "2020-05-12T09:16:52Z"
  },
  {
    "id": 16007581,
    "headline": "Disney Plans Another Bonds Offering With A Six-Part Deal",
    "summary": "The Walt Disney Company (NYSE: DIS) is planning a second debt offering this year, according to its filing with the Securities and Exchange Commission.",
    "symbols": [
      "AAPL",
      "BA",
      "BNPQY",
      "CS",
      "DIS",
      "GS",
      "MS",
      "PYPL"
    ],
    "source": "",
    "url": "https://www.benzinga.com/news/20/05/16007581/disney-plans-another-bonds-offering-with-a-six-part-deal",
    "created_at": "2020-05-12T08:57:07Z"
  },
  {
    "id": 16007502,
    "headline": "Twitter To Remove Coronavirus Misinformation, Including That Tweeted By Trump",
    "summary": "Twitter Inc. (NYSE: TWTR) announced on Monday that it will start labeling novel coronavirus (COVID-19) related information for misleading or contested claims starting the same day.",
    "symbols": [
      "FB",
      "GOOGL",
      "TWTR"
    ],
    "source": "",
    "url": "https://www.benzinga.com/news/20/05/16007502/twitter-to-remove-coronavirus-misinformation-including-that-tweeted-by-trump",
    "created_at": "2020-05-12T07:50:03Z"
  },
  {
    "id": 16007407,
    "headline": "PayPal Raises $4B In Debt Offering As Business Surges During Pandemic",
    "summary": "PayPal Holdings Inc. (NASDAQ: PYPL) on Monday announced that it raised $4 billion in a corporate bond offering.",
    "symbols": [
      "PYPL"
    ],
    "source": "",
    "url": "https://www.benzinga.com/news/20/05/16007407/paypal-raises-4b-in-debt-offering-as-business-surges-during-pandemic",
    "created_at": "2020-05-12T04:10:52Z"
  },
  {
    "id": 16007360,
    "headline": "'Jim Cramer reviews top 10 stocks 'for this difficult moment' on the 'Cramer Covid-19 Index'' -CNBC",
    "summary": "",
    "symbols": [
      "BYND",
      "COUP",
      "DXCM",
      "EVBG",
      "LVGO",
      "MASI",
      "MRNA",
      "NET",
      "PTON",
      "SQ"
    ],
    "source": "",
    "url": "https://www.benzinga.com/trading-ideas/20/05/16007360/jim-cramer-reviews-top-10-stocks-for-this-difficult-moment-on-the-cramer-covid-19-index-cnbc",
    "created_at": "2020-05-12T01:48:44Z"
  }
]