[
  {
    "id": 15350476,
    "headline": "Apple Says Outside of China, Customer Demand Across Product and Service Categories Has Been Strong to Date and in Line With Expectations",
    "summary": "",
    "symbols": [
      "AAPL"
    ],
    "source": "",
    "url": "https://www.benzinga.com/node/15350476",
    "created_at": "2020-02-17T23:59:35Z"
  },
  {
    "id": 15350475,
    "headline": "Apple Says iPhone Supply Shortages Will Temporarily Affect Revenues Worldwide; Says Demand for Products Within China Has Been Affected",
    "summary": "",
    "symbols": [
      "AAPL"
    ],
    "source": "",
    "url": "https://www.benzinga.com/node/15350475",
    "created_at": "2020-02-17T23:59:08Z"
  },
  {
    "id": 15350473,
    "headline": "Apple Says iPhone Manufacturing Partner Sites Located Outside Hubei Are Ramping Up More Slowly Than Had Anticipated ; Says Worldwide iPhone Supply Will Be Temporarily Constrained",
    "summary": "",
    "symbols": [
      "AAPL"
    ],
    "source": "",
    "url": "https://www.benzinga.com/node/15350473",
    "created_at": "2020-02-17T23:58:03Z"
  },
  {
    "id": 15350472,
    "headline": "Apple Says Do Not Expect to Meet Revenue Guidance Provided for March Quarter Due to Two Main Factors; Says Work is Starting to Resume Around China , But We Are Experiencing a Slower Return to Normal Conditions Than We Had Anticipated",
    "summary": "",
    "symbols": [
      "AAPL"
    ],
    "source": "",
    "url": "https://www.benzinga.com/node/15350472",
    "created_at": "2020-02-17T23:57:17Z"
  },
  {
    "id": 15349543,
    "headline": "Today's Pickup: Uncertain Contract Status Leads DHL To Issue Potential Notice Of layoffs In Michigan",
    "summary": "",
    "symbols": [
      "AMZN",
      "CVTI",
      "FCAU",
      "FDX",
      "GM",
      "UPS"
    ],
    "source": "",
    "url": "https://www.benzinga.com/node/15349543",
    "created_at": "2020-02-17T17:32:20Z"
  },
  {
    "id": 15341461,
    "headline": "Here's How Much Investing $100 In Walmart Stock Back In 2010 Would Be Worth Today",
    "summary": "",
    "symbols": [
      "AMZN",
      "SPY",
      "WMT"
    ],
    "source": "",
    "url": "https://www.benzinga.com/node/15341461",
    "created_at": "2020-02-17T16:56:49Z"
  },
  {
    "id": 15347573,
    "headline": "Borderlands: project44 Promotes Freight Visibility In The USMCA Era; Mexico Auto Industry Prepares For Coronavirus",
    "summary": "",
    "symbols": [
      "AMZN"
    ],
    "source": "",
    "url": "https://www.benzinga.com/node/15347573",
    "created_at": "2020-02-17T16:25:46Z"
  },
  {
    "id": 15349116,
    "headline": "Duda Launches App Store After Announcing $25M Investment Round",
    "summary": "",
    "symbols": [
      "GDDY",
      "GOOG"
    ],
    "source": "",
    "url": "https://www.benzinga.com/node/15349116",
    "created_at": "2020-02-17T14:49:55Z"
  },
  {
    "id": 15345451,
    "headline": "Amazon Purges Three Last-Mile Vendors This Week",
    "summary": "",
    "symbols": [
      "AMZN"
    ],
    "source": "",
    "url": "https://www.benzinga.com/node/15345451",
    "created_at": "2020-02-17T14:12:25Z"
  },
  {
    "id": 15348609,
    "headline": "Trump Administration Said to Weigh Limits on Use of U.S. Semiconductor Manufacturing Equipment Which Would Target Huawei; Could Affect Semiconductor Industry Beyond China",
    "summary": "",
    "symbols": [
      "AMAT",
      "FXI",
      "LRCX",
      "TSM"
    ],
    "source": "",
    "url": "https://www.benzinga.com/node/15348609",
    "created_at": "2020-02-17T12:40:46Z"
  }
]